mis/__init__.py
mis/_backends/__init__.py
mis/_backends/data.py
mis/_backends/types.py
mis/_backends/backends/__init__.py
mis/_backends/backends/base_backend.py
mis/_backends/backends/get_backend.py
mis/_backends/backends/local_backends.py
mis/_backends/backends/remote_backends.py
mis/coloring/__init__.py
mis/coloring/coloring.py
mis/data/__init__.py
mis/data/dataloader.py
mis/data/graphs.py
mis/pipeline/__init__.py
mis/pipeline/basesolver.py
mis/pipeline/config.py
mis/pipeline/embedder.py
mis/pipeline/fixtures.py
mis/pipeline/kernelization.py
mis/pipeline/layout.py
mis/pipeline/maximization.py
mis/pipeline/postprocessor.py
mis/pipeline/preprocessor.py
mis/pipeline/pulse.py
mis/shared/__init__.py
mis/shared/error.py
mis/shared/graphs.py
mis/shared/retrier.py
mis/shared/types.py
mis/solver/greedymapping.py
mis/solver/solver.py
maximum_independent_set-0.3.1.dist-info/METADATA
maximum_independent_set-0.3.1.dist-info/WHEEL
maximum_independent_set-0.3.1.dist-info/licenses/LICENSE
maximum_independent_set-0.3.1.dist-info/RECORD
