Metadata-Version: 2.4
Name: maximum-independent-set
Version: 0.3.1
Summary: A Python library designed to help users design classical- and quantum-driven solutions for the Maximum Independent Set (MIS) problem.
Project-URL: Documentation, https://pasqal-io.github.io/maximum-independent-set/latest/
Project-URL: Issues, https://github.com/pasqal-io/maximum-independent-set/issues
Project-URL: Source, https://github.com/pasqal-io/maximum-independent-set
Author-email: Manu Lahariya <manu.lahariya@pasqal.com>, David Teller <david.teller@pasqal.com>, Roland Guichard <roland.guichard@pasqal.com>, Charles Moussa <c.moussa@pasqal.com>
License: MIT-derived
License-File: LICENSE
Keywords: quantum
Classifier: Development Status :: 4 - Beta
Classifier: Programming Language :: Python
Classifier: Programming Language :: Python :: 3.10
Classifier: Programming Language :: Python :: 3.11
Classifier: Programming Language :: Python :: 3.12
Classifier: Programming Language :: Python :: 3.13
Classifier: Programming Language :: Python :: Implementation :: CPython
Classifier: Programming Language :: Python :: Implementation :: PyPy
Requires-Python: >=3.10
Requires-Dist: geopy
Requires-Dist: matplotlib
Requires-Dist: networkx
Requires-Dist: numpy
Requires-Dist: pandas
Requires-Dist: qoolqit[solvers]==0.2.1
Requires-Dist: torch
Requires-Dist: torch-geometric
Provides-Extra: extras
Requires-Dist: jupyter; extra == 'extras'
Requires-Dist: tqdm; extra == 'extras'
